{
	"metaDataVersion": "1.0.0",
	"category": "com.microchip.ide.project",
	"content": {
		"metaDataVersion": "1.1.0",
		"name": "com.microchip.mcu32.mplabx.project.csp_apps_sam_d21_da1_conf_da1_eic_led_on_off",
		"version": "3.2.0",
		"displayName": "EIC Interrupt Example for SAM D21/DA1 Family",
		"projectName": "eic_led_on_off_sam_da1_xpro",
		"shortDescription": "This example application demonstrates how to generate interrupt using the EIC on switch press and indicate it through an LED.",
		"ide": {
			"name": "MPLABX",
			"semverRange": ">=5.50.0"
		},
		"compiler": [
			{
				"name": "XC32",
				"semverRange": ">=3.1.0"
			}
		],
		"dfp": {
			"name": "SAMDA1_DFP",
			"semverRange": "^2.3.56"
		},
		"configurator": {
			"name": "MHC",
			"semverRange": ">=3.8.0"
		},
		"device": {
			"metaDataVersion": "1.0.0",
			"category": "com.microchip.portal.contentRef",
			"content": {
				"metaDataVersion": "1.0.0",
				"category": "com.microchip.device",
				"name": "ATSAMDA1J16B",
				"versionRange": "*"
			}
		},
		"author": "Microchip",
		"subcategories": [
			[
				"Development Kit",
				"SAM DA1 Xplained Pro Evaluation Kit"
			],
			[
				"Harmony",
				"Peripherals",
				"EIC"
			],
			[
				"Peripherals",
				"EIC"
			]
		],
		"peripherals": [
			"EIC"
		],
		"keywords": [
			"MHC",
			"Harmony",
			"ATSAMDA1J16B",
			"SAM D21/DA1 Family",
			"EIC",
			"Interrupts",
			"Interrupt Controller",
			"External Interrupt Controller"
		],
		"additionalData": {
			"longDescription": {
				"metaDataVersion": "1.0.0",
				"category": "com.microchip.portal.fileRef",
				"content": {
					"metaDataVersion": "1.0.0",
					"fileName": "./../../readme.md",
					"mimeType": "text/markdown"
				}
			}
		}
	}
}